{"cameraMode":{"drawMode":0,"name":"Shaded","section":"Shading Mode"},"sceneLighting":false,"audioPlay":false,"sceneViewState":{"m_AlwaysRefresh":false,"showFog":false,"showSkybox":false,"showFlares":false,"showImageEffects":false,"showParticleSystems":false,"showVisualEffectGraphs":true,"m_FxEnabled":true},"in2DMode":false,"pivot":{"x":0.33428919315338137,"y":-0.44461071491241457,"z":-0.929842472076416},"rotation":{"x":-0.04552460089325905,"y":0.9497296810150147,"z":-0.2622300088405609,"w":-0.16487516462802888},"size":2.00827693939209,"orthographic":false}